student_marksheet/__init__.py
student_marksheet/marksheet.py
student_marksheet-0.1.0.dist-info/licenses/LICENSE
student_marksheet-0.1.0.dist-info/METADATA
student_marksheet-0.1.0.dist-info/WHEEL
student_marksheet-0.1.0.dist-info/top_level.txt
student_marksheet-0.1.0.dist-info/RECORD
