Metadata-Version: 2.4
Name: student-marksheet
Version: 0.1.0
Summary: A simple Python library for generating student marksheets.
Author-email: Swami <blockswitching@gmail.com>
License: The MIT License (MIT)
Project-URL: Homepage, https://github.com/blockswitching/student_marksheet_module
Project-URL: Repository, https://github.com/blockswitching/student_marksheet_module
Project-URL: Issues, https://github.com/blockswitching/student_marksheet_module/issues
Keywords: marksheet,education,students,grading
Requires-Python: >=3.7
License-File: LICENSE
Dynamic: license-file
